ollama_coder/__init__.py
ollama_coder/__main__.py
ollama_coder/cli.py
ollama_coder-0.2.3.dist-info/licenses/LICENSE
ollama_coder-0.2.3.dist-info/METADATA
ollama_coder-0.2.3.dist-info/WHEEL
ollama_coder-0.2.3.dist-info/entry_points.txt
ollama_coder-0.2.3.dist-info/top_level.txt
ollama_coder-0.2.3.dist-info/RECORD
