Metadata-Version: 2.4
Name: ollama-coder
Version: 0.2.3
Summary: Agentic coding assistant for Ollama - Claude Code alternative
Author: Lalo Morales
License-Expression: MIT
Project-URL: Homepage, https://github.com/lalomorales22/ollama-coder
Project-URL: Repository, https://github.com/lalomorales22/ollama-coder
Project-URL: Issues, https://github.com/lalomorales22/ollama-coder/issues
Keywords: ollama,cli,agent,coding-assistant,ai,llm,autonomous
Classifier: Development Status :: 3 - Alpha
Classifier: Environment :: Console
Classifier: Programming Language :: Python :: 3
Classifier: Programming Language :: Python :: 3 :: Only
Requires-Python: >=3.9
License-File: LICENSE
Requires-Dist: ollama>=0.4.0
Provides-Extra: rich
Requires-Dist: rich>=13.0.0; extra == "rich"
Dynamic: license-file
